pax1000_controller/__init__.py
pax1000_controller/pax1000_controller.py
pax1000_controller-0.0.2.dist-info/METADATA
pax1000_controller-0.0.2.dist-info/WHEEL
pax1000_controller-0.0.2.dist-info/licenses/LICENSE
pax1000_controller-0.0.2.dist-info/RECORD
