Metadata-Version: 2.4
Name: pax1000_controller
Version: 0.0.2
Summary: A library to controlle the Thorlabs PAX1000 polarimeter
Project-URL: Homepage, https://github.com/UP-Smart-Soft-Matter/PAX1000-controller
Project-URL: Issues, https://github.com/UP-Smart-Soft-Matter/PAX1000-controller/issues
Author-email: Mika Music <mika.music@uni-potsdam.de>
License-Expression: LGPL-2.1-only
License-File: LICENSE
Classifier: Operating System :: OS Independent
Classifier: Programming Language :: Python :: 3
Requires-Python: >=3.9
